CHANGES.md
LICENSE
MANIFEST.in
README.rst
metadataparsing.py
setup.py
pelican_metadataparsing.egg-info/PKG-INFO
pelican_metadataparsing.egg-info/SOURCES.txt
pelican_metadataparsing.egg-info/dependency_links.txt
pelican_metadataparsing.egg-info/not-zip-safe
pelican_metadataparsing.egg-info/requires.txt
pelican_metadataparsing.egg-info/top_level.txt