Metadata-Version: 1.1
Name: pelican-metadataparsing
Version: 0.1.0
Summary: Allow definition of custom metadata parsers for Pelican content
Home-page: https://github.com/AlexJF/pelican-metadataparsing
Author: Alexandre Fonseca
Author-email: alexandrejorgefonseca@gmail.com
License: Apache
Download-URL: https://github.com/AlexJF/pelican-metadataparsing/archive/v0.1.0.zip
Keywords: pelican blog static metadata parser
Platform: UNKNOWN
